{
	"https://api.lunarush.io/v1/game-api/api/battle/boss/user": "st=8YqhyyKveIjA9Gvi4t15eA&e=1652643794&va=1.12.0",
	"https://api.lunarush.io/v1/game-api/api/hero/boss": "st=-qp4x0KvyhgnF8ajHitBTA&e=1652643763&va=1.12.0",
	"https://api.lunarush.io/v1/game-api/api/hero/active": "st=l68YM4xS8LccYDlKqrIwhw&e=1652643763&va=1.12.0",
	"https://api.lunarush.io/v1/game-api/api/battle/boss": "st=Mp22EDYzu-hAi1SYG9VROg&e=1652643783&va=1.12.0",
	"https://api.lunarush.io/v1/core-api/api/user/me": "st=CBFIu5O73DT2ZhenvLWLxQ&e=1652643808&va=1.12.0",
	"https://api.lunarush.io/v1/core-api/api/user/roi": "st=LuB1ohgJ4zPWc1vhRYEGTg&e=1652643804&va=1.12.0"
}