{
	"https://api.lunarush.io/v1/core-api/api/user/roi": "st=XpsJiw0fYPqZJdIK5qBQ5Q&e=1653601011&va=1.12.0",
	"https://api.lunarush.io/v1/core-api/api/user/me": "st=ekm_7IF2zaYGmn6HHW36hA&e=1653601015&va=1.12.0",
	"https://api.lunarush.io/v1/game-api/api/battle/boss/user": "st=-TqbaXV594SXS8FmaiXZHQ&e=1653601001&va=1.12.0",
	"https://api.lunarush.io/v1/game-api/api/battle/boss/daily_list": "st=w1vzzYkDHH8Qt66FhKtT2Q&e=1653533082&va=1.12.0",
	"https://api.lunarush.io/v1/game-api/api/hero/boss": "st=bmJJENKYOPPrqFijvyv3gA&e=1653600958&va=1.12.0",
	"https://api.lunarush.io/v1/game-api/api/hero/active": "st=ajZ2LBs6W2_UA7cFEiX8VQ&e=1653600958&va=1.12.0",
	"https://api.lunarush.io/v1/game-api/api/battle/boss": "st=3vlni78XsQzVD01Z26IdxA&e=1653600974&va=1.12.0"
}