{
	"https://api.lunarush.io/v1/core-api/api/user/roi": "st=KHAThAlD05iULYNolj-61Q&e=1653608093&va=1.12.0",
	"https://api.lunarush.io/v1/core-api/api/user/me": "st=Gf8w1Sxjpp8RQ72sSjbq7g&e=1653608097&va=1.12.0",
	"https://api.lunarush.io/v1/game-api/api/battle/boss/user": "st=Xs5noBuiDeMFtHjxc-hCUw&e=1653608102&va=1.12.0",
	"https://api.lunarush.io/v1/game-api/api/battle/boss/daily_list": "st=w1vzzYkDHH8Qt66FhKtT2Q&e=1653533082&va=1.12.0",
	"https://api.lunarush.io/v1/game-api/api/hero/boss": "st=h3i0Sz4Gm6KPsktgoxpOzw&e=1653608041&va=1.12.0",
	"https://api.lunarush.io/v1/game-api/api/hero/active": "st=pXUh0t1vqcZ9BHF1T38W3A&e=1653608041&va=1.12.0",
	"https://api.lunarush.io/v1/game-api/api/battle/boss": "st=CpO--Zayc3RxZlrEe_34uA&e=1653608058&va=1.12.0"
}