{
	"https://api.lunarush.io/v1/core-api/api/user/me": "st=V2EAejO51V082rKVH5jpSg&e=1653751794&va=1.12.0",
	"https://api.lunarush.io/v1/game-api/api/battle/boss/user": "st=kZ2MSgHbs0KGrgutzoXaig&e=1653751790&va=1.12.0",
	"https://api.lunarush.io/v1/core-api/api/user/roi": "st=gG-dzWHnIbZ-A5WZsfjylw&e=1653751737&va=1.12.0",
	"https://api.lunarush.io/v1/game-api/api/hero/boss": "st=lYFdyqQwWh_GJAdNdDSeDQ&e=1653751750&va=1.12.0",
	"https://api.lunarush.io/v1/game-api/api/hero/active": "st=qcBYaCdF0R9pKVnE3v68qA&e=1653751750&va=1.12.0",
	"https://api.lunarush.io/v1/game-api/api/battle/boss": "st=ch5Fy7D5dd9IEN7jBBvlEw&e=1653751767&va=1.12.0"
}