{
	"https://api.lunarush.io/v1/game-api/api/battle/boss/user": "st=DwK52vxBW-ltnBx1Vk0fMQ&e=1652641994&va=1.12.0",
	"https://api.lunarush.io/v1/game-api/api/hero/boss": "st=M_DjPNy0_5UtcCq2D4kBBQ&e=1652641964&va=1.12.0",
	"https://api.lunarush.io/v1/game-api/api/hero/active": "st=FP_y4WWcz_ubExUB4MrMcQ&e=1652641964&va=1.12.0",
	"https://api.lunarush.io/v1/game-api/api/battle/boss": "st=LZURilfHNwtSkII3KdEVYg&e=1652641984&va=1.12.0",
	"https://api.lunarush.io/v1/core-api/api/user/me": "st=kWS5Zgs7v1sjd7LvH4MJqQ&e=1652642008&va=1.12.0",
	"https://api.lunarush.io/v1/core-api/api/user/roi": "st=tTo9dkoh-Qxaf60NtSESog&e=1652642004&va=1.12.0"
}