{
	"https://api.lunarush.io/v1/core-api/api/user/roi": "st=3tWQ8v-Q6RTRmQkmlO4kCA&e=1654059341&va=1.12.0",
	"https://api.lunarush.io/v1/core-api/api/user/me": "st=swZHxKzU8EGnDTYE_4rgQg&e=1654059345&va=1.12.0",
	"https://api.lunarush.io/v1/game-api/api/battle/boss/user": "st=FUtDpJjYazOK5ibVr05Kfw&e=1654059350&va=1.12.0",
	"https://api.lunarush.io/v1/game-api/api/hero/boss": "st=zMd6aY4CiOz_2YSYU2zMVg&e=1654059354&va=1.12.0",
	"https://api.lunarush.io/v1/game-api/api/hero/active": "st=68_Ui2LD1dC-Qsnv3iryHA&e=1654059354&va=1.12.0",
	"https://api.lunarush.io/v1/game-api/api/battle/boss": "st=0O92nzEZLyPKqQfrCey-pQ&e=1654059371&va=1.12.0",
	"https://api.lunarush.io/v1/game-api/api/battle/boss/daily_list": "st=P5UQIRLLaIuo4r8CgQ_3Kw&e=1654041941&va=1.12.0"
}