{
	"https://api.lunarush.io/v1/core-api/api/user/me": "st=qyqQLX0_cw7eO7p2SidfPw&e=1653172727&va=1.12.0",
	"https://api.lunarush.io/v1/core-api/api/user/roi": "st=lKnFG8cbz7j9LNO73zN3bg&e=1653172723&va=1.12.0",
	"https://api.lunarush.io/v1/game-api/api/battle/boss/user": "st=GUxDJMFXrszgZgfua_mA7w&e=1653172731&va=1.12.0",
	"https://api.lunarush.io/v1/game-api/api/hero/boss": "st=g3U1e8XqI9W6QM0VwskNtA&e=1653172735&va=1.12.0",
	"https://api.lunarush.io/v1/game-api/api/hero/active": "st=FM633GcDZbx5sj2vXQtwUA&e=1653172735&va=1.12.0",
	"https://api.lunarush.io/v1/game-api/api/battle/boss": "st=WDL_oQxMtQVEHewUuay_DA&e=1653172752&va=1.12.0"
}