{
	"https://api.lunarush.io/v1/game-api/api/battle/boss/user": "st=QBTrKuBuzqEhjjHYcfq-gA&e=1653916771&va=1.12.0",
	"https://api.lunarush.io/v1/core-api/api/user/me": "st=imcGKWdnidLny93iswGqEw&e=1653916766&va=1.12.0",
	"https://api.lunarush.io/v1/core-api/api/user/roi": "st=1qGNYynwPgjHetXxM9BFEQ&e=1653916762&va=1.12.0",
	"https://api.lunarush.io/v1/game-api/api/hero/active": "st=PW1FMlZZwoDk_dOlQpidQg&e=1653916774&va=1.12.0",
	"https://api.lunarush.io/v1/game-api/api/hero/boss": "st=VeuEVjfSdd0b9tYkmXYNDA&e=1653916774&va=1.12.0",
	"https://api.lunarush.io/v1/game-api/api/battle/boss": "st=44bj-XwDzhzvYDKSPe-4zw&e=1653916791&va=1.12.0"
}