{
	"https://api.lunarush.io/v1/core-api/api/user/me": "st=giCwgXjz0LcFYtjkQXGzew&e=1653335854&va=1.12.0",
	"https://api.lunarush.io/v1/core-api/api/user/roi": "st=PL5l_Dy8RFKH6r858rU6cQ&e=1653335742&va=1.12.0",
	"https://api.lunarush.io/v1/game-api/api/battle/boss/user": "st=zJedOKoIabvfs9C0iL278Q&e=1653335732&va=1.12.0",
	"https://api.lunarush.io/v1/game-api/api/hero/boss": "st=Hq9OboMwH-XPzzUiTKe5CA&e=1653335693&va=1.12.0",
	"https://api.lunarush.io/v1/game-api/api/hero/active": "st=q-jx19_p701tlZBg8htEeQ&e=1653335693&va=1.12.0",
	"https://api.lunarush.io/v1/game-api/api/battle/boss": "st=kYE9Gw8aIzlSxO0gErdQAg&e=1653335710&va=1.12.0"
}