{
	"https://api.lunarush.io/v1/game-api/api/battle/boss/user": "st=9EPv6c0vEwrlYAiYNBIZSg&e=1652680187&va=1.12.0",
	"https://api.lunarush.io/v1/game-api/api/hero/boss": "st=ShMjndy2xQQg-jLNab89KQ&e=1652680191&va=1.12.0",
	"https://api.lunarush.io/v1/game-api/api/hero/active": "st=YNNlTk87YlrrOpa9sTXwQw&e=1652680191&va=1.12.0",
	"https://api.lunarush.io/v1/game-api/api/battle/boss": "st=Tt3Sz3mSaYTXIr1hG4QmcQ&e=1652680110&va=1.12.0",
	"https://api.lunarush.io/v1/core-api/api/user/me": "st=tx565iCdgkYjDWlPZzHAGQ&e=1652680184&va=1.12.0",
	"https://api.lunarush.io/v1/core-api/api/user/roi": "st=MVrkN-1WkxXQrLRMWMKI2w&e=1652680180&va=1.12.0",
	"https://api.lunarush.io/v1/game-api/api/battle/boss/daily_list": "st=i5XZCF2mlYbgu34JIdGYsw&e=1652659538&va=1.12.0"
}