{
	"https://api.lunarush.io/v1/core-api/api/user/me": "st=hAo4P20f75D53ZuFr5JqsQ&e=1653735004&va=1.12.0",
	"https://api.lunarush.io/v1/core-api/api/user/roi": "st=vdXd77K8BYHRcNtknroZhA&e=1653735000&va=1.12.0",
	"https://api.lunarush.io/v1/game-api/api/battle/boss/user": "st=MI9gdMmEl0KorKOUnzSjHA&e=1653734990&va=1.12.0",
	"https://api.lunarush.io/v1/game-api/api/hero/boss": "st=iy0VqTCx32alp-UZLPt2xA&e=1653734950&va=1.12.0",
	"https://api.lunarush.io/v1/game-api/api/hero/active": "st=suqVVsOLQ6zHLkA4ZPDkng&e=1653734950&va=1.12.0",
	"https://api.lunarush.io/v1/game-api/api/battle/boss": "st=bCPAHlII2WVoPYSs_F1AKA&e=1653734967&va=1.12.0",
	"https://api.lunarush.io/v1/game-api/api/battle/boss/daily_list": "st=JJVfRiippHRo380MkAPQFQ&e=1653700355&va=1.12.0"
}