{
	"https://api.lunarush.io/v1/core-api/api/user/me": "st=2Alp-N8FGMYITSvtBhdySg&e=1653393450&va=1.12.0",
	"https://api.lunarush.io/v1/core-api/api/user/roi": "st=XgL3Z_xVCFP-K8MXMmqcUw&e=1653393446&va=1.12.0",
	"https://api.lunarush.io/v1/game-api/api/battle/boss/user": "st=AHDZQY0Ywvh07kfzns6-uA&e=1653393436&va=1.12.0",
	"https://api.lunarush.io/v1/game-api/api/hero/boss": "st=wPWrPy9y_0DHzVnsEgymAg&e=1653393397&va=1.12.0",
	"https://api.lunarush.io/v1/game-api/api/hero/active": "st=VWKIhCgVSwKfX3Za-dX9ww&e=1653393397&va=1.12.0",
	"https://api.lunarush.io/v1/game-api/api/battle/boss": "st=ZpkFADv5a7ychtCxmmVyIg&e=1653393354&va=1.12.0"
}