{
	"https://api.lunarush.io/v1/core-api/api/user/me": "st=_inaNHeJwp9sbRJWalR0-w&e=1652722892&va=1.12.0",
	"https://api.lunarush.io/v1/core-api/api/user/roi": "st=bP7nd93nsqvebJp4ynYYsw&e=1652722888&va=1.12.0",
	"https://api.lunarush.io/v1/game-api/api/battle/boss/user": "st=gWJGCmj53MhEwUiGlqU2sg&e=1652722927&va=1.12.0",
	"https://api.lunarush.io/v1/game-api/api/hero/boss": "st=xh7Pkgh458h9BiIVSxX2ZQ&e=1652722900&va=1.12.0",
	"https://api.lunarush.io/v1/game-api/api/hero/active": "st=rfv62Ecl7owab7ubZaRVeQ&e=1652722900&va=1.12.0",
	"https://api.lunarush.io/v1/game-api/api/battle/boss": "st=v2tsumqWUytyhXLy0oq99g&e=1652722917&va=1.12.0"
}