{
	"https://api.lunarush.io/v1/core-api/api/user/me": "st=BqW0LMFY7D6u60EVXkBFqQ&e=1653409606&va=1.12.0",
	"https://api.lunarush.io/v1/core-api/api/user/roi": "st=YFZhf7yoXNLnVr25_zyhOg&e=1653409547&va=1.12.0",
	"https://api.lunarush.io/v1/game-api/api/battle/boss/user": "st=YUcEjgn4Cp5sTLFbE-7O8w&e=1653409610&va=1.12.0",
	"https://api.lunarush.io/v1/game-api/api/hero/boss": "st=oN80O9DgSWGgWo9T96clXA&e=1653409614&va=1.12.0",
	"https://api.lunarush.io/v1/game-api/api/hero/active": "st=svc9ZC0dpQtPfMPTUMCV6A&e=1653409614&va=1.12.0",
	"https://api.lunarush.io/v1/game-api/api/battle/boss": "st=MunQcN0Z-RjLsrY_bPYcRA&e=1653409631&va=1.12.0"
}