{
	"https://api.lunarush.io/v1/game-api/api/battle/boss/user": "st=AJKTl2CfOcZPGdHMNgXZjQ&e=1653944059&va=1.12.0",
	"https://api.lunarush.io/v1/core-api/api/user/me": "st=y7GysEkn345bHajUpoVHyw&e=1653944063&va=1.12.0",
	"https://api.lunarush.io/v1/core-api/api/user/roi": "st=-I5IcWTotKCWyvbB5dQmOg&e=1653944069&va=1.12.0",
	"https://api.lunarush.io/v1/game-api/api/hero/active": "st=9rHMXL_UHT6xJmc6nD8GpA&e=1653944017&va=1.12.0",
	"https://api.lunarush.io/v1/game-api/api/hero/boss": "st=gbSJEMgoaLTeBZlIwayq2g&e=1653944017&va=1.12.0",
	"https://api.lunarush.io/v1/game-api/api/battle/boss": "st=43tbp02gA7jOt88MK_lkPA&e=1653944034&va=1.12.0"
}