{
	"https://api.lunarush.io/v1/game-api/api/battle/boss/user": "st=TkXh0Nwi4Z6ru_m4JQYF-A&e=1652917969&va=1.12.0",
	"https://api.lunarush.io/v1/core-api/api/user/me": "st=shv8zXZcQHIhS2cjbcg22Q&e=1652917973&va=1.12.0",
	"https://api.lunarush.io/v1/core-api/api/user/roi": "st=H5BIdYFLGlWiHpv2J5s33Q&e=1652917979&va=1.12.0",
	"https://api.lunarush.io/v1/game-api/api/hero/boss": "st=di7grB6foe1AMBpsbtiHYA&e=1652917932&va=1.12.0",
	"https://api.lunarush.io/v1/game-api/api/hero/active": "st=WpICA8wSo5E2DRrSnS-5OA&e=1652917932&va=1.12.0",
	"https://api.lunarush.io/v1/game-api/api/battle/boss": "st=x7MTK49dnR2Pp6wMWZgcyw&e=1652917949&va=1.12.0"
}