{
	"https://api.lunarush.io/v1/core-api/api/user/me": "st=q8aXssuqqb-2c2ruHMvaqg&e=1653515349&va=1.12.0",
	"https://api.lunarush.io/v1/game-api/api/battle/boss/user": "st=MX7SyhSja5h7W20r5F8nsQ&e=1653515396&va=1.12.0",
	"https://api.lunarush.io/v1/game-api/api/hero/boss": "st=vp-pSNw0hC7hGt157SMGxw&e=1653515358&va=1.12.0",
	"https://api.lunarush.io/v1/game-api/api/hero/active": "st=VheddFrSOlXERy8qXC50xw&e=1653515358&va=1.12.0",
	"https://api.lunarush.io/v1/core-api/api/user/roi": "st=9UltV_nSvqoM-5fml5RTSw&e=1653515345&va=1.12.0",
	"https://api.lunarush.io/v1/game-api/api/battle/boss": "st=R6wPLwUEcPmHcBkasZLQ4A&e=1653515375&va=1.12.0"
}