{
	"https://api.lunarush.io/v1/core-api/api/user/me": "st=by__HNhBvz8J2jX_HeFycQ&e=1653414429&va=1.12.0",
	"https://api.lunarush.io/v1/core-api/api/user/roi": "st=5ilhJr-Zlz_a868I0IMgDQ&e=1653414373&va=1.12.0",
	"https://api.lunarush.io/v1/game-api/api/battle/boss/user": "st=SoVAOluPuE2cYAdz7u_nLQ&e=1653414425&va=1.12.0",
	"https://api.lunarush.io/v1/game-api/api/hero/boss": "st=urAqWSIw_-IHox2NBMClrQ&e=1653414386&va=1.12.0",
	"https://api.lunarush.io/v1/game-api/api/hero/active": "st=_6992hWiXKupjPyP2eiGkg&e=1653414386&va=1.12.0",
	"https://api.lunarush.io/v1/game-api/api/battle/boss": "st=FH3cAhTwOlCuesk7pAYyWg&e=1653414402&va=1.12.0"
}