{
	"https://api.lunarush.io/v1/core-api/api/user/me": "st=xkE5uxUUhS-JA6-dCdErPg&e=1653700964&va=1.12.0",
	"https://api.lunarush.io/v1/core-api/api/user/roi": "st=Z2dt-RXf9pVeH1MMpbsZ3Q&e=1653700957&va=1.12.0",
	"https://api.lunarush.io/v1/game-api/api/battle/boss/user": "st=7T41F14Yiq33VeDyWwTV1Q&e=1653700968&va=1.12.0",
	"https://api.lunarush.io/v1/game-api/api/hero/boss": "st=TIZ7w4I9cSKD4C7cefGzhg&e=1653700972&va=1.12.0",
	"https://api.lunarush.io/v1/game-api/api/hero/active": "st=0IV6re5WzSihsIUGvaRtNg&e=1653700972&va=1.12.0",
	"https://api.lunarush.io/v1/game-api/api/battle/boss": "st=fdFHOLkunGWXg_-Exe3Osg&e=1653700989&va=1.12.0",
	"https://api.lunarush.io/v1/game-api/api/battle/boss/daily_list": "st=JJVfRiippHRo380MkAPQFQ&e=1653700355&va=1.12.0"
}