{
	"https://api.lunarush.io/v1/game-api/api/battle/boss/user": "st=sgOGgX2YWtqokT6gjUhieA&e=1652673043&va=1.12.0",
	"https://api.lunarush.io/v1/game-api/api/hero/boss": "st=VKcrwSYdHibg1eASOHTvpw&e=1652673012&va=1.12.0",
	"https://api.lunarush.io/v1/game-api/api/hero/active": "st=J3IQhEhIknGyvST4rMZexQ&e=1652673012&va=1.12.0",
	"https://api.lunarush.io/v1/game-api/api/battle/boss": "st=ksg-8Gj9HA1Gu4kdd6UELA&e=1652673032&va=1.12.0",
	"https://api.lunarush.io/v1/core-api/api/user/me": "st=Er9TK05VOTL2TnlDjnCs5A&e=1652673047&va=1.12.0",
	"https://api.lunarush.io/v1/core-api/api/user/roi": "st=xWFSncgb5LGj3hcmBiCWpw&e=1652673001&va=1.12.0",
	"https://api.lunarush.io/v1/game-api/api/battle/boss/daily_list": "st=i5XZCF2mlYbgu34JIdGYsw&e=1652659538&va=1.12.0"
}