{
	"https://api.lunarush.io/v1/core-api/api/user/me": "st=LzAz6dNIz2BNuS-Jghs7ZQ&e=1653508672&va=1.12.0",
	"https://api.lunarush.io/v1/game-api/api/battle/boss/user": "st=ga-Xd_TcPWPxTKCmGSHauw&e=1653508668&va=1.12.0",
	"https://api.lunarush.io/v1/game-api/api/hero/boss": "st=31EEE0aeaUW6bkbMilKNNA&e=1653508631&va=1.12.0",
	"https://api.lunarush.io/v1/game-api/api/hero/active": "st=wltwSQzHVILKtrntNbID6g&e=1653508631&va=1.12.0",
	"https://api.lunarush.io/v1/core-api/api/user/roi": "st=C_iQadY9xbTscxLRagxkZw&e=1653508678&va=1.12.0",
	"https://api.lunarush.io/v1/game-api/api/battle/boss": "st=BWLgM03NpIo71PqegKV3Rw&e=1653508531&va=1.12.0"
}