{
	"https://api.lunarush.io/v1/core-api/api/user/me": "st=FyKbmLPWbuH_8aJkhBbtNw&e=1653808558&va=1.12.0",
	"https://api.lunarush.io/v1/game-api/api/battle/boss/user": "st=1bq9YgnFE7hdG8X4bPnqMw&e=1653808563&va=1.12.0",
	"https://api.lunarush.io/v1/core-api/api/user/roi": "st=xudLONRpaCKqzuy6l1QwVg&e=1653808554&va=1.12.0",
	"https://api.lunarush.io/v1/game-api/api/hero/boss": "st=3Tm23jurIhpZAbpAM3NgXg&e=1653808567&va=1.12.0",
	"https://api.lunarush.io/v1/game-api/api/hero/active": "st=JjumB08e127bDLGQ903Hbg&e=1653808567&va=1.12.0",
	"https://api.lunarush.io/v1/game-api/api/battle/boss": "st=Xh6F2Oy-HLrbIReM9mETKA&e=1653808584&va=1.12.0",
	"https://api.lunarush.io/v1/game-api/api/battle/boss/daily_list": "st=c_mWJrLAI3FNExlAGASOgQ&e=1653782756&va=1.12.0"
}