{
	"https://api.lunarush.io/v1/core-api/api/user/me": "st=Dfm2YiKCjkrRdM0VL8IY6A&e=1653803116&va=1.12.0",
	"https://api.lunarush.io/v1/game-api/api/battle/boss/user": "st=qE6yy_Xk6uJ8AMdsfcfwPg&e=1653803101&va=1.12.0",
	"https://api.lunarush.io/v1/core-api/api/user/roi": "st=C-Kyqkirgv-k01Jw7E0Gbw&e=1653803111&va=1.12.0",
	"https://api.lunarush.io/v1/game-api/api/hero/boss": "st=PZjYd8XfE9yEzpdxhCwmUQ&e=1653803059&va=1.12.0",
	"https://api.lunarush.io/v1/game-api/api/hero/active": "st=AdBqW29MRhjOaFQaZ5Pmqw&e=1653803059&va=1.12.0",
	"https://api.lunarush.io/v1/game-api/api/battle/boss": "st=PPnQZyAq_GL-83jFgC1Cag&e=1653803076&va=1.12.0",
	"https://api.lunarush.io/v1/game-api/api/battle/boss/daily_list": "st=c_mWJrLAI3FNExlAGASOgQ&e=1653782756&va=1.12.0"
}