{
	"https://api.lunarush.io/v1/core-api/api/user/me": "st=j-GsgnsCwt8loEFp3cX2-Q&e=1653802680&va=1.12.0",
	"https://api.lunarush.io/v1/game-api/api/battle/boss/user": "st=xEfXOWuDlLsc4uTNi3Vwlg&e=1653802685&va=1.12.0",
	"https://api.lunarush.io/v1/core-api/api/user/roi": "st=jH-yrNLRxjCqbHWP3-969A&e=1653802676&va=1.12.0",
	"https://api.lunarush.io/v1/game-api/api/hero/boss": "st=XHTeKRpEufGkos6OSd659Q&e=1653802689&va=1.12.0",
	"https://api.lunarush.io/v1/game-api/api/hero/active": "st=D-dOcLYZCFUqUgvRM_DBbQ&e=1653802689&va=1.12.0",
	"https://api.lunarush.io/v1/game-api/api/battle/boss": "st=h4XIOC9wczTzaLKXZwDXlw&e=1653802643&va=1.12.0",
	"https://api.lunarush.io/v1/game-api/api/battle/boss/daily_list": "st=c_mWJrLAI3FNExlAGASOgQ&e=1653782756&va=1.12.0"
}