{
	"https://api.lunarush.io/v1/core-api/api/user/roi": "st=97Q9UU_kid1xCsaZEJPSsw&e=1653563732&va=1.12.0",
	"https://api.lunarush.io/v1/core-api/api/user/me": "st=ALaFzzvYX3GMpHr8E5e2eA&e=1653563736&va=1.12.0",
	"https://api.lunarush.io/v1/game-api/api/battle/boss/user": "st=1002yfz45G_OHmElWmFaeA&e=1653563741&va=1.12.0",
	"https://api.lunarush.io/v1/game-api/api/battle/boss/daily_list": "st=w1vzzYkDHH8Qt66FhKtT2Q&e=1653533082&va=1.12.0",
	"https://api.lunarush.io/v1/game-api/api/hero/boss": "st=AZ3W05mV37BqtgySEP6Dmw&e=1653563744&va=1.12.0",
	"https://api.lunarush.io/v1/game-api/api/hero/active": "st=KmGEq6sNdIIT9azAgnmfmg&e=1653563745&va=1.12.0",
	"https://api.lunarush.io/v1/game-api/api/battle/boss": "st=0CiQCRyfJ_Af86CFj7TH1g&e=1653563699&va=1.12.0"
}