{
	"https://api.lunarush.io/v1/core-api/api/user/roi": "st=nfdwGNarx8ylE00IgrtQVg&e=1654075506&va=1.12.0",
	"https://api.lunarush.io/v1/core-api/api/user/me": "st=yHTpib1O6yjvT1jdB_12Ng&e=1654075510&va=1.12.0",
	"https://api.lunarush.io/v1/game-api/api/battle/boss/user": "st=nBOxqrdYxUIRR1-Jh8X0Kw&e=1654075497&va=1.12.0",
	"https://api.lunarush.io/v1/game-api/api/hero/boss": "st=l1jL07zm4WdLrXO8jxMclA&e=1654075458&va=1.12.0",
	"https://api.lunarush.io/v1/game-api/api/hero/active": "st=IbUCpOvl8b-LJpcv4eKUkA&e=1654075458&va=1.12.0",
	"https://api.lunarush.io/v1/game-api/api/battle/boss": "st=djmAoTIzLGXlruEGOn3ldQ&e=1654075475&va=1.12.0",
	"https://api.lunarush.io/v1/game-api/api/battle/boss/daily_list": "st=P5UQIRLLaIuo4r8CgQ_3Kw&e=1654041941&va=1.12.0"
}