{
	"https://api.lunarush.io/v1/core-api/api/user/me": "st=wgGXNrbho-HLVXTDOIiU6g&e=1653463550&va=1.12.0",
	"https://api.lunarush.io/v1/core-api/api/user/roi": "st=XA_4OL-qDie3AvMaI3ga4A&e=1653463547&va=1.12.0",
	"https://api.lunarush.io/v1/game-api/api/battle/boss/user": "st=8vHbMH2m2G58sP9jzaNV1Q&e=1653463537&va=1.12.0",
	"https://api.lunarush.io/v1/game-api/api/hero/boss": "st=jK1WeNxl0Y7PDQ9q-uXNdQ&e=1653463498&va=1.12.0",
	"https://api.lunarush.io/v1/game-api/api/hero/active": "st=YI0riX8aXNmBd2UqeZErEA&e=1653463498&va=1.12.0",
	"https://api.lunarush.io/v1/game-api/api/battle/boss": "st=GeRWAgeyoZiI8APWfPP5CQ&e=1653463456&va=1.12.0",
	"https://api.lunarush.io/v1/game-api/api/battle/boss/daily_list": "st=O4LhCR6AAEM3n86_7z1UTA&e=1653437154&va=1.12.0"
}