{
	"https://api.lunarush.io/v1/core-api/api/user/roi": "st=U4p4UBaz1E8SGpyQxW4qsA&e=1654082882&va=1.12.0",
	"https://api.lunarush.io/v1/core-api/api/user/me": "st=MqvYC456egWJi15ijmJZMw&e=1654082886&va=1.12.0",
	"https://api.lunarush.io/v1/game-api/api/battle/boss/user": "st=kJBOnsKw1tCPvJrZ5ppRFA&e=1654082891&va=1.12.0",
	"https://api.lunarush.io/v1/game-api/api/hero/boss": "st=TzNXf3FCSHT5xfpAFm4-DQ&e=1654082894&va=1.12.0",
	"https://api.lunarush.io/v1/game-api/api/hero/active": "st=QQr090H0y-o_8p8A1My7HA&e=1654082894&va=1.12.0",
	"https://api.lunarush.io/v1/game-api/api/battle/boss": "st=JyRSzMHMZONbIW_MtIuAQA&e=1654082911&va=1.12.0",
	"https://api.lunarush.io/v1/game-api/api/battle/boss/daily_list": "st=P5UQIRLLaIuo4r8CgQ_3Kw&e=1654041941&va=1.12.0"
}