{
	"https://api.lunarush.io/v1/game-api/api/battle/boss/user": "st=sOPYfyW_-axCys0Wt2bACA&e=1652916546&va=1.12.0",
	"https://api.lunarush.io/v1/core-api/api/user/me": "st=iUgpWABBNy9Nmkx6d73oGw&e=1652916542&va=1.12.0",
	"https://api.lunarush.io/v1/core-api/api/user/roi": "st=9G2JFmmOOM1yELRreZ3ovw&e=1652916537&va=1.12.0",
	"https://api.lunarush.io/v1/game-api/api/hero/boss": "st=JAd8qXD0uI8G8z4KsKbpRA&e=1652916550&va=1.12.0",
	"https://api.lunarush.io/v1/game-api/api/hero/active": "st=lCfeX2AI4a-OGrT0a-ZLog&e=1652916550&va=1.12.0",
	"https://api.lunarush.io/v1/game-api/api/battle/boss": "st=Aa9kSYkRtk-IhEaixGPBPw&e=1652916509&va=1.12.0"
}