{
	"https://api.lunarush.io/v1/core-api/api/user/me": "st=vs_xvT-OUKAQVcYCjYn9Vw&e=1653505016&va=1.12.0",
	"https://api.lunarush.io/v1/game-api/api/battle/boss/user": "st=Lvh2BC55uE97E9RsUVx96A&e=1653505003&va=1.12.0",
	"https://api.lunarush.io/v1/game-api/api/hero/boss": "st=W5tLgl9w5dZOtopJyiB8qg&e=1653504963&va=1.12.0",
	"https://api.lunarush.io/v1/game-api/api/hero/active": "st=Z559EFeL98KLjpZndACOFw&e=1653504963&va=1.12.0",
	"https://api.lunarush.io/v1/core-api/api/user/roi": "st=Uf09apGzDdoDf91htuyr5Q&e=1653505012&va=1.12.0",
	"https://api.lunarush.io/v1/game-api/api/battle/boss": "st=MEsl6LtQsaEvHUVFX-v8fg&e=1653504981&va=1.12.0"
}