{
	"https://api.lunarush.io/v1/core-api/api/user/roi": "st=2AIJX6fXUsRBmnM2nxZQzQ&e=1653571335&va=1.12.0",
	"https://api.lunarush.io/v1/core-api/api/user/me": "st=Qpi18TNbHb3jWpvR2BeaQQ&e=1653571330&va=1.12.0",
	"https://api.lunarush.io/v1/game-api/api/battle/boss/user": "st=VIn-J0lAETASlMrK7d2k8w&e=1653571325&va=1.12.0",
	"https://api.lunarush.io/v1/game-api/api/battle/boss/daily_list": "st=w1vzzYkDHH8Qt66FhKtT2Q&e=1653533082&va=1.12.0",
	"https://api.lunarush.io/v1/game-api/api/hero/boss": "st=K8c0XvIxJ-eFUCK1SlWy_w&e=1653571286&va=1.12.0",
	"https://api.lunarush.io/v1/game-api/api/hero/active": "st=CVDmjm5LhzA8X-lGdo9gjA&e=1653571286&va=1.12.0",
	"https://api.lunarush.io/v1/game-api/api/battle/boss": "st=AjjcjIguS4rNrHRLqnukIQ&e=1653571303&va=1.12.0"
}