{
	"https://api.lunarush.io/v1/core-api/api/user/me": "st=jlzzLficv2NYbW3pwIFGIw&e=1653320639&va=1.12.0",
	"https://api.lunarush.io/v1/core-api/api/user/roi": "st=XEnOcypDkL19DH1i781b_Q&e=1653320645&va=1.12.0",
	"https://api.lunarush.io/v1/game-api/api/battle/boss/user": "st=sbKggqKSMd9h1FlGwimmlQ&e=1653320635&va=1.12.0",
	"https://api.lunarush.io/v1/game-api/api/hero/boss": "st=NqY6UUmODzmmvjfvE1COsA&e=1653320597&va=1.12.0",
	"https://api.lunarush.io/v1/game-api/api/hero/active": "st=7h8h6ZhckdFUeD6qDSI05A&e=1653320597&va=1.12.0",
	"https://api.lunarush.io/v1/game-api/api/battle/boss": "st=R6YOlxaQ8r1VKFSZfyTsTg&e=1653320557&va=1.12.0"
}