{
	"https://api.lunarush.io/v1/core-api/api/user/me": "st=o5P4y-6AHq7gWIMZtiijGQ&e=1653214508&va=1.12.0",
	"https://api.lunarush.io/v1/core-api/api/user/roi": "st=xHu-VV1Sgg75pz4AXswFvg&e=1653214452&va=1.12.0",
	"https://api.lunarush.io/v1/game-api/api/battle/boss/user": "st=V92sncwov_zDd1RmpB55ng&e=1653214504&va=1.12.0",
	"https://api.lunarush.io/v1/game-api/api/hero/boss": "st=j5Xn7oAjhtZ6CjhbkJWdnA&e=1653214465&va=1.12.0",
	"https://api.lunarush.io/v1/game-api/api/hero/active": "st=Y7SNh9layVWZ3SLz8fe8aw&e=1653214465&va=1.12.0",
	"https://api.lunarush.io/v1/game-api/api/battle/boss": "st=ObpE2By0BGdI8V09OES-fw&e=1653214482&va=1.12.0",
	"https://api.lunarush.io/v1/game-api/api/battle/boss/daily_list": "st=pum9fU5IRlr_6vn6ft9lOw&e=1653177914&va=1.12.0"
}