{
	"https://api.lunarush.io/v1/core-api/api/user/me": "st=1W1J68_XRqfgUGsRKHuFTg&e=1653454791&va=1.12.0",
	"https://api.lunarush.io/v1/core-api/api/user/roi": "st=8DBRGZ3SjALN4GnYSIpZOg&e=1653454787&va=1.12.0",
	"https://api.lunarush.io/v1/game-api/api/battle/boss/user": "st=VNJJPw9IWM7MhCFSanTGHQ&e=1653454794&va=1.12.0",
	"https://api.lunarush.io/v1/game-api/api/hero/boss": "st=jD3_omoFDtxun8_1PjM-yw&e=1653454798&va=1.12.0",
	"https://api.lunarush.io/v1/game-api/api/hero/active": "st=I30CUawHX0swCrDlNSsh-Q&e=1653454798&va=1.12.0",
	"https://api.lunarush.io/v1/game-api/api/battle/boss": "st=R6p_9RDmpXs86UP9PVR0Kw&e=1653454815&va=1.12.0",
	"https://api.lunarush.io/v1/game-api/api/battle/boss/daily_list": "st=O4LhCR6AAEM3n86_7z1UTA&e=1653437154&va=1.12.0"
}