{
	"https://api.lunarush.io/v1/core-api/api/user/me": "st=2Iz5qGEPg_k156bW_iaggA&e=1652816228&va=1.12.0",
	"https://api.lunarush.io/v1/core-api/api/user/roi": "st=F8KchCtoFDshNZLbiSRSUQ&e=1652816224&va=1.12.0",
	"https://api.lunarush.io/v1/game-api/api/battle/boss/user": "st=OyIHnC2LM6mTlnSR0_yLVw&e=1652816214&va=1.12.0",
	"https://api.lunarush.io/v1/game-api/api/hero/boss": "st=v5ll8jYtTppJoLtvwcIU1A&e=1652816185&va=1.12.0",
	"https://api.lunarush.io/v1/game-api/api/hero/active": "st=kuyyFX0BSvznU_QvuMp6Og&e=1652816185&va=1.12.0",
	"https://api.lunarush.io/v1/game-api/api/battle/boss": "st=_uR47R6H2bICzKWzXAI7Ag&e=1652816202&va=1.12.0",
	"https://api.lunarush.io/v1/game-api/api/battle/boss/daily_list": "st=KzZzAj4oqHxwgrtoUT7R3A&e=1652745940&va=1.12.0"
}