{
	"https://api.lunarush.io/v1/core-api/api/user/roi": "st=9ELjuRlQfkfDLSLi_7aZdw&e=1653558112&va=1.12.0",
	"https://api.lunarush.io/v1/core-api/api/user/me": "st=28wLyySv1pRArDVppKa4IQ&e=1653558116&va=1.12.0",
	"https://api.lunarush.io/v1/game-api/api/battle/boss/user": "st=Ml3W4S2PntDAptZypOnl1w&e=1653558103&va=1.12.0",
	"https://api.lunarush.io/v1/game-api/api/battle/boss/daily_list": "st=w1vzzYkDHH8Qt66FhKtT2Q&e=1653533082&va=1.12.0",
	"https://api.lunarush.io/v1/game-api/api/hero/boss": "st=GkIwn_874gs108yRV-_faA&e=1653558063&va=1.12.0",
	"https://api.lunarush.io/v1/game-api/api/hero/active": "st=5qk_lo8WKl-3sMgEbRX_dg&e=1653558064&va=1.12.0",
	"https://api.lunarush.io/v1/game-api/api/battle/boss": "st=HYHptYKtDu6CALpH19nTmw&e=1653558080&va=1.12.0"
}