{
	"https://api.lunarush.io/v1/core-api/api/user/me": "st=MIuLMQp4vNkknYsKEWbEqw&e=1653205151&va=1.12.0",
	"https://api.lunarush.io/v1/core-api/api/user/roi": "st=Cv-XmxTkPd1I45974FMd9Q&e=1653205157&va=1.12.0",
	"https://api.lunarush.io/v1/game-api/api/battle/boss/user": "st=KmGQPKhMd_6WFtevMtUlHQ&e=1653205147&va=1.12.0",
	"https://api.lunarush.io/v1/game-api/api/hero/boss": "st=12qMzasTWhKNuWcq-SnXag&e=1653205108&va=1.12.0",
	"https://api.lunarush.io/v1/game-api/api/hero/active": "st=xl9pqdFlhK4_dwc8OF99dA&e=1653205108&va=1.12.0",
	"https://api.lunarush.io/v1/game-api/api/battle/boss": "st=Q3JpG3xR8a4lTcwerxd8KA&e=1653205125&va=1.12.0",
	"https://api.lunarush.io/v1/game-api/api/battle/boss/daily_list": "st=pum9fU5IRlr_6vn6ft9lOw&e=1653177914&va=1.12.0"
}