{
	"https://api.lunarush.io/v1/core-api/api/user/me": "st=7tcu31R_vSzTeG3wGOUmXQ&e=1652967917&va=1.12.0",
	"https://api.lunarush.io/v1/core-api/api/user/roi": "st=XImzQ4UwI7J_CSkLHs4NRw&e=1652967913&va=1.12.0",
	"https://api.lunarush.io/v1/game-api/api/battle/boss/user": "st=Tr-dK6w-Z8aWe01wElZWJQ&e=1652967921&va=1.12.0",
	"https://api.lunarush.io/v1/game-api/api/hero/boss": "st=G4aHtjlaRS-6uPjWckIqyg&e=1652967925&va=1.12.0",
	"https://api.lunarush.io/v1/game-api/api/hero/active": "st=h8s3BBijs8fUQGWeOPviBA&e=1652967925&va=1.12.0",
	"https://api.lunarush.io/v1/game-api/api/battle/boss": "st=aY82qXUydLIp0_0kjBc6aA&e=1652967942&va=1.12.0"
}