{
	"https://api.lunarush.io/v1/game-api/api/battle/boss/user": "st=svhVtGwSTHMQ_LGfAa5tyw&e=1653995824&va=1.12.0",
	"https://api.lunarush.io/v1/core-api/api/user/me": "st=Qf0eCuw_HhL9-xNyNsTPbQ&e=1653995820&va=1.12.0",
	"https://api.lunarush.io/v1/core-api/api/user/roi": "st=5IF8zQwH3gFkRPfrOMgxxw&e=1653995813&va=1.12.0",
	"https://api.lunarush.io/v1/game-api/api/hero/active": "st=PBrr1twT22qVUphULr7DFw&e=1653995828&va=1.12.0",
	"https://api.lunarush.io/v1/game-api/api/hero/boss": "st=vlCcIYRB0RRGzQWePh_rvg&e=1653995828&va=1.12.0",
	"https://api.lunarush.io/v1/game-api/api/battle/boss": "st=87AORa3Inx8d8bi3bYedqg&e=1653995845&va=1.12.0",
	"https://api.lunarush.io/v1/game-api/api/battle/boss/daily_list": "st=Bj9_lzMkNi9SkgmnLhgcHg&e=1653955513&va=1.12.0"
}