{
	"https://api.lunarush.io/v1/core-api/api/user/roi": "st=Qigo1kUfzAvEptMkg16w7A&e=1654097144&va=1.12.0",
	"https://api.lunarush.io/v1/core-api/api/user/me": "st=BGWxewOf2siaF9y4spgBhg&e=1654097148&va=1.12.0",
	"https://api.lunarush.io/v1/game-api/api/battle/boss/user": "st=GD5t5DYEYmDpqCTnqfBGqg&e=1654097153&va=1.12.0",
	"https://api.lunarush.io/v1/game-api/api/hero/boss": "st=k7Dtof4mn9RMn19xcymZgQ&e=1654097157&va=1.12.0",
	"https://api.lunarush.io/v1/game-api/api/hero/active": "st=y30WcS2N9fbkJO7fj9SFWw&e=1654097157&va=1.12.0",
	"https://api.lunarush.io/v1/game-api/api/battle/boss": "st=HrL3ZgzZMSmgcs6blJKQOw&e=1654097176&va=1.12.0",
	"https://api.lunarush.io/v1/game-api/api/battle/boss/daily_list": "st=P5UQIRLLaIuo4r8CgQ_3Kw&e=1654041941&va=1.12.0"
}