{
	"https://api.lunarush.io/v1/game-api/api/battle/boss/user": "st=zLuq_yVY_inISKl03C1dPw&e=1652674240&va=1.12.0",
	"https://api.lunarush.io/v1/game-api/api/hero/boss": "st=6iptWWO1JDCeOLSDaKziKg&e=1652674243&va=1.12.0",
	"https://api.lunarush.io/v1/game-api/api/hero/active": "st=Cm4T6Ts9a1xqkcM49NjPfw&e=1652674243&va=1.12.0",
	"https://api.lunarush.io/v1/game-api/api/battle/boss": "st=g-RJRDUYvsz8XxabY7Hlgg&e=1652674263&va=1.12.0",
	"https://api.lunarush.io/v1/core-api/api/user/me": "st=Mc4nw_Sh1Ok7IGvgy_yQxQ&e=1652674236&va=1.12.0",
	"https://api.lunarush.io/v1/core-api/api/user/roi": "st=gT7ZGj17i-dTD099ylvD1w&e=1652674232&va=1.12.0",
	"https://api.lunarush.io/v1/game-api/api/battle/boss/daily_list": "st=i5XZCF2mlYbgu34JIdGYsw&e=1652659538&va=1.12.0"
}