{
	"https://api.lunarush.io/v1/core-api/api/user/me": "st=ruXgXMvMymtTmSFFo6wcbQ&e=1653425004&va=1.12.0",
	"https://api.lunarush.io/v1/core-api/api/user/roi": "st=zkU8OkL9jjAOYYeAE2oDcw&e=1653425000&va=1.12.0",
	"https://api.lunarush.io/v1/game-api/api/battle/boss/user": "st=22PZBoKDtm6LNgHux--LyQ&e=1653425008&va=1.12.0",
	"https://api.lunarush.io/v1/game-api/api/hero/boss": "st=1swEFJupYmfc1NqDcK2tfA&e=1653424951&va=1.12.0",
	"https://api.lunarush.io/v1/game-api/api/hero/active": "st=RuieOawD9lopgBegjUcV_g&e=1653424951&va=1.12.0",
	"https://api.lunarush.io/v1/game-api/api/battle/boss": "st=6xXGFIirI6R5RHhw6i-hHg&e=1653424968&va=1.12.0"
}