{
	"https://api.lunarush.io/v1/core-api/api/user/roi": "st=dfeOzHekfufpqVpuCcZ8eg&e=1653611630&va=1.12.0",
	"https://api.lunarush.io/v1/core-api/api/user/me": "st=fZzV5hvzqgc-XkIZdQWZmQ&e=1653611634&va=1.12.0",
	"https://api.lunarush.io/v1/game-api/api/battle/boss/user": "st=lFAoJ0NZkhF6_iSxhq-G1Q&e=1653611638&va=1.12.0",
	"https://api.lunarush.io/v1/game-api/api/battle/boss/daily_list": "st=2dJpeyAEaSXK3ruUg03ZcQ&e=1653609978&va=1.12.0",
	"https://api.lunarush.io/v1/game-api/api/hero/boss": "st=IFBWjEvzDufONeF6MUv3PA&e=1653611642&va=1.12.0",
	"https://api.lunarush.io/v1/game-api/api/hero/active": "st=pzFjbsIp_VVjr5WVF5NNvg&e=1653611642&va=1.12.0",
	"https://api.lunarush.io/v1/game-api/api/battle/boss": "st=Dxx-NhexxgYdkl3t1jgHKg&e=1653611535&va=1.12.0"
}