{
	"https://api.lunarush.io/v1/core-api/api/user/roi": "st=A4HOHJGgITKd3M8yiPytIw&e=1654093319&va=1.12.0",
	"https://api.lunarush.io/v1/core-api/api/user/me": "st=_vyZTYbULU1lKuPnXGUIIA&e=1654093323&va=1.12.0",
	"https://api.lunarush.io/v1/game-api/api/battle/boss/user": "st=9HNX75dk9Kvzb0jjC8T7Rg&e=1654093369&va=1.12.0",
	"https://api.lunarush.io/v1/game-api/api/hero/boss": "st=Sayapra9ghnlgfX5d3DXWg&e=1654093331&va=1.12.0",
	"https://api.lunarush.io/v1/game-api/api/hero/active": "st=trhCpTon8M9UhNDCtTtwQA&e=1654093331&va=1.12.0",
	"https://api.lunarush.io/v1/game-api/api/battle/boss": "st=1Ry2DMqCfzeRKMdGm7Z8zA&e=1654093349&va=1.12.0",
	"https://api.lunarush.io/v1/game-api/api/battle/boss/daily_list": "st=P5UQIRLLaIuo4r8CgQ_3Kw&e=1654041941&va=1.12.0"
}