{
	"https://api.lunarush.io/v1/core-api/api/user/me": "st=5Z8Y07xgSLp8V405-J-NUA&e=1653461662&va=1.12.0",
	"https://api.lunarush.io/v1/core-api/api/user/roi": "st=9xY7P0apiq9RBc1xdrBuFw&e=1653461657&va=1.12.0",
	"https://api.lunarush.io/v1/game-api/api/battle/boss/user": "st=m4PlkkvmD1jdijTEx6f0Uw&e=1653461712&va=1.12.0",
	"https://api.lunarush.io/v1/game-api/api/hero/boss": "st=6Fcof2Mhw97ISELuNsyblg&e=1653461669&va=1.12.0",
	"https://api.lunarush.io/v1/game-api/api/hero/active": "st=0q146M9ca0mtGcdOruie8Q&e=1653461669&va=1.12.0",
	"https://api.lunarush.io/v1/game-api/api/battle/boss": "st=4iTrvqguf_YpeNFPNInPEw&e=1653461686&va=1.12.0",
	"https://api.lunarush.io/v1/game-api/api/battle/boss/daily_list": "st=O4LhCR6AAEM3n86_7z1UTA&e=1653437154&va=1.12.0"
}